pyillustrator/__init__.py
pyillustrator/config.py
pyillustrator/plots.py
pyillustrator/utils.py
pyillustrator-0.9.6.dist-info/licenses/LICENSE
pyillustrator-0.9.6.dist-info/METADATA
pyillustrator-0.9.6.dist-info/WHEEL
pyillustrator-0.9.6.dist-info/top_level.txt
pyillustrator-0.9.6.dist-info/RECORD
