Metadata-Version: 2.4
Name: pyillustrator
Version: 0.9.6
Summary: A Python module for generating various plots using Matplotlib
Home-page: https://github.com/ipatazas/pyillustrator
Author: Isaac
Author-email: Isaac Robledo Martin <isaac.robledo.martin@gmail.com>
License: MIT
Project-URL: Homepage, https://github.com/ipatazas/pyillustrator
Classifier: Programming Language :: Python :: 3
Classifier: License :: OSI Approved :: MIT License
Classifier: Operating System :: OS Independent
Requires-Python: >=3.6
License-File: LICENSE
Requires-Dist: matplotlib>=3.0.0
Requires-Dist: numpy>=1.26.0
Dynamic: author
Dynamic: home-page
Dynamic: license-file
Dynamic: requires-python
